python_typesolver/__init__.py
typesolver-0.0.0.dist-info/METADATA
typesolver-0.0.0.dist-info/WHEEL
typesolver-0.0.0.dist-info/RECORD
