Metadata-Version: 2.1
Name: typesolver
Version: 0.0.0
Summary: Type based rule engine.
Author-Email: Niklas Rosenstein <rosensteinniklas@gmail.com>
License: MIT
Requires-Python: >=3.10
